{
    "id": "org.kde.konquest",
    "runtime": "org.kde.Platform",
    "runtime-version": "6.8",
    "sdk": "org.kde.Sdk",
    "command": "konquest",
    "rename-icon": "konquest",
    "finish-args": [
        "--device=dri",
        "--share=ipc",
        "--socket=fallback-x11",
        "--socket=wayland"
    ],
    "modules": [
        {
            "name": "libkdegames",
            "buildsystem": "cmake-ninja",
            "sources": [
                {
                    "type": "archive",
                    "url": "https://download.kde.org/stable/release-service/24.12.2/src/libkdegames-24.12.2.tar.xz",
                    "sha256": "b3129c537c44d8bbd3ad87c272044efa5c164cae1f56e8fd54a50e7a6c7773da",
                    "x-checker-data": {
                        "type": "anitya",
                        "project-id": 8763,
                        "stable-only": true,
                        "url-template": "https://download.kde.org/stable/release-service/$version/src/libkdegames-$version.tar.xz"
                    }
                }
            ]
        },
        {
            "name": "konquest",
            "buildsystem": "cmake-ninja",
            "config-opts": [
                "-DCMAKE_BUILD_TYPE=RelWithDebInfo"
            ],
            "builddir": true,
            "sources": [
                {
                    "type": "archive",
                    "url": "https://download.kde.org/stable/release-service/24.12.2/src/konquest-24.12.2.tar.xz",
                    "sha256": "ee8db311c3da07a53a1ab1fed91b0d7cd3965ac98aef4f3c25512fa04f77e7d4",
                    "x-checker-data": {
                        "type": "anitya",
                        "project-id": 8763,
                        "stable-only": true,
                        "url-template": "https://download.kde.org/stable/release-service/$version/src/konquest-$version.tar.xz"
                    }
                }
            ]
        }
    ]
}
